tabkan/__init__.py
tabkan/mixer.py
tabkan/models.py
tabkan/trainer.py
tabkan/transfer_learning.py
tabkan/tuner.py
tabkan-1.0.1.dist-info/METADATA
tabkan-1.0.1.dist-info/WHEEL
tabkan-1.0.1.dist-info/top_level.txt
tabkan-1.0.1.dist-info/RECORD
