Metadata-Version: 2.4
Name: tabkan
Version: 1.0.1
Summary: TabKAN: A Framework for Advancing Tabular Data Analysis using Kolmogorov-Arnold Networks
Home-page: https://github.com/aseslamian/TabKAN
Author: Ali Eslamian, Alireza Afzal Aghaei, Qiang Cheng
Author-email: ali.eslamian@uky.edu
Classifier: Programming Language :: Python :: 3
Classifier: License :: OSI Approved :: MIT License
Classifier: Operating System :: OS Independent
Classifier: Intended Audience :: Science/Research
Classifier: Topic :: Scientific/Engineering :: Artificial Intelligence
Requires-Python: >=3.9
Requires-Dist: torch>=2.0
Requires-Dist: numpy>=1.22
Requires-Dist: scikit-learn
Requires-Dist: optuna>=3.0
Requires-Dist: pandas
Requires-Dist: tqdm
Requires-Dist: pykan
Requires-Dist: fkan
Requires-Dist: rkan
Dynamic: author
Dynamic: author-email
Dynamic: classifier
Dynamic: description
Dynamic: description-content-type
Dynamic: home-page
Dynamic: requires-dist
Dynamic: requires-python
Dynamic: summary
